pydantic_ssm_settings/__init__.py
pydantic_ssm_settings/settings.py
pydantic_ssm_settings/source.py
pydantic_ssm_settings-1.1.2.dist-info/LICENSE
pydantic_ssm_settings-1.1.2.dist-info/METADATA
pydantic_ssm_settings-1.1.2.dist-info/WHEEL
pydantic_ssm_settings-1.1.2.dist-info/top_level.txt
pydantic_ssm_settings-1.1.2.dist-info/RECORD
