Metadata-Version: 2.2
Name: pydantic-ssm-settings
Version: 1.1.2
Summary: AWS SSM support for Pydantic Settings
Requires-Python: >=3.9
License-File: LICENSE
Requires-Dist: pydantic-settings>=2
